[
    {
        "title": "$:/plugins/whitefall/obsidian-manager",
        "name": "obsidian-manager",
        "author": "whitefall",
        "description": "",
        "plugin-type": "plugin",
        "version": "0.0.1",
        "list": "readme",
        "dependents": "",
        "type": "application/json",
        "Modern.TiddlyDev#SHA256-Hashed": "5470b695c0dd399e1901b8e6bd0afed7c75d40adc7c96fbf6cb3d7711c5d8867",
        "readme": "! obsidian-manager\n\n",
        "requires-reload": "yes"
    }
]